{
  "$schema": "https://raw.githubusercontent.com/spdx/spdx-spec/v2.2.1/schemas/spdx-schema.json",
  "spdxVersion": "SPDX-2.2",
  "dataLicense": "CC0-1.0",
  "SPDXID": "SPDXRef-DOCUMENT",
  "documentNamespace": "https://spdx.org/spdxdocs/ada-url-x64-linux-2.7.7-3eaef4fe-c867-4acf-8564-f0cc29cf1df8",
  "name": "ada-url:x64-linux@2.7.7 231c7d99649266a3633f85d0ed97e0f99be55c257475972fa3d2df05f66f0c7e",
  "creationInfo": {
    "creators": [
      "Tool: vcpkg-2024-07-10-d2dfc73769081bdd9b782d08d27794780b7a99b9"
    ],
    "created": "2024-07-17T09:48:04Z"
  },
  "relationships": [
    {
      "spdxElementId": "SPDXRef-port",
      "relationshipType": "GENERATES",
      "relatedSpdxElement": "SPDXRef-binary"
    },
    {
      "spdxElementId": "SPDXRef-port",
      "relationshipType": "CONTAINS",
      "relatedSpdxElement": "SPDXRef-file-0"
    },
    {
      "spdxElementId": "SPDXRef-port",
      "relationshipType": "CONTAINS",
      "relatedSpdxElement": "SPDXRef-file-1"
    },
    {
      "spdxElementId": "SPDXRef-port",
      "relationshipType": "CONTAINS",
      "relatedSpdxElement": "SPDXRef-file-2"
    },
    {
      "spdxElementId": "SPDXRef-binary",
      "relationshipType": "GENERATED_FROM",
      "relatedSpdxElement": "SPDXRef-port"
    },
    {
      "spdxElementId": "SPDXRef-file-0",
      "relationshipType": "CONTAINED_BY",
      "relatedSpdxElement": "SPDXRef-port"
    },
    {
      "spdxElementId": "SPDXRef-file-1",
      "relationshipType": "CONTAINED_BY",
      "relatedSpdxElement": "SPDXRef-port"
    },
    {
      "spdxElementId": "SPDXRef-file-2",
      "relationshipType": "CONTAINED_BY",
      "relatedSpdxElement": "SPDXRef-port"
    }
  ],
  "packages": [
    {
      "name": "ada-url",
      "SPDXID": "SPDXRef-port",
      "versionInfo": "2.7.7",
      "downloadLocation": "NOASSERTION",
      "homepage": "https://ada-url.com/",
      "licenseConcluded": "MIT",
      "licenseDeclared": "NOASSERTION",
      "copyrightText": "NOASSERTION",
      "description": "WHATWG-compliant and fast URL parser written in modern C++",
      "comment": "This is the port (recipe) consumed by vcpkg."
    },
    {
      "name": "ada-url:x64-linux",
      "SPDXID": "SPDXRef-binary",
      "versionInfo": "231c7d99649266a3633f85d0ed97e0f99be55c257475972fa3d2df05f66f0c7e",
      "downloadLocation": "NONE",
      "licenseConcluded": "MIT",
      "licenseDeclared": "NOASSERTION",
      "copyrightText": "NOASSERTION",
      "comment": "This is a binary package built by vcpkg."
    },
    {
      "SPDXID": "SPDXRef-resource-1",
      "name": "ada-url/ada",
      "downloadLocation": "git+https://github.com/ada-url/ada@v2.7.7",
      "licenseConcluded": "NOASSERTION",
      "licenseDeclared": "NOASSERTION",
      "copyrightText": "NOASSERTION",
      "checksums": [
        {
          "algorithm": "SHA512",
          "checksumValue": "987782dacee5115f061f5579257fddf3ed26cdb8654279ce47915bef03abe7ca9904f0f4082b774be23772a3400925e908db45d9da935c7683269aae0ac2186a"
        }
      ]
    }
  ],
  "files": [
    {
      "fileName": ".//opt/vcpkg/ports/ada-url/no-cpm.patch",
      "SPDXID": "SPDXRef-file-0",
      "checksums": [
        {
          "algorithm": "SHA256",
          "checksumValue": "1b51073f983c1874414cf63f82e384ea021dbba355d8e6e71f90c40ebbadd46c"
        }
      ],
      "licenseConcluded": "NOASSERTION",
      "copyrightText": "NOASSERTION"
    },
    {
      "fileName": ".//opt/vcpkg/ports/ada-url/vcpkg.json",
      "SPDXID": "SPDXRef-file-1",
      "checksums": [
        {
          "algorithm": "SHA256",
          "checksumValue": "2ffac39e8efd3688c506181f34e8343d06eb0abd264ebd24d05384a4507ae86f"
        }
      ],
      "licenseConcluded": "NOASSERTION",
      "copyrightText": "NOASSERTION"
    },
    {
      "fileName": ".//opt/vcpkg/ports/ada-url/portfile.cmake",
      "SPDXID": "SPDXRef-file-2",
      "checksums": [
        {
          "algorithm": "SHA256",
          "checksumValue": "bce4b200841455cae412ebadc62420f63dc96d9f08f0df608620e5a8faa7e204"
        }
      ],
      "licenseConcluded": "NOASSERTION",
      "copyrightText": "NOASSERTION"
    }
  ]
}
